[{"Entity_type": "Per", "Text": "St. Lawrence", "Start": "136", "End": "140"}, {"Entity_type": "Loc", "Text": "Lund", "Start": "145", "End": "146"}, {"Entity_type": "Loc", "Text": "the university town of Schonen", "Start": "6", "End": "15"}, {"Entity_type": "Loc", "Text": "the town of Lund", "Start": "17", "End": "24"}, {"Entity_type": "Fac", "Text": "church", "Start": "166", "End": "167"}, {"Entity_type": "Per", "Text": "giant", "Start": "216", "End": "217"}, {"Entity_type": "Per", "Text": " St. Lawrence ", "Start": "241", "End": "247"}, {"Entity_type": "Per", "Text": "St. Lawrence", "Start": "270", "End": "274"}, {"Entity_type": "Per", "Text": "giant", "Start": "288", "End": "289"}, {"Entity_type": "Per", "Text": "The saint", "Start": "317", "End": "320"}, {"Entity_type": "Per", "Text": "St. Lawrence", "Start": "362", "End": "366"}, {"Entity_type": "Per", "Text": "Finn", "Start": "544", "End": "545"}, {"Entity_type": "Per", "Text": "St. Lawrence", "Start": "596", "End": "600"}, {"Entity_type": "Per", "Text": "giant ", "Start": "656", "End": "658"}, {"Entity_type": "Per", "Text": "Finn", "Start": "704", "End": "705"}, {"Entity_type": "Per", "Text": "Finn", "Start": "707", "End": "708"}, {"Entity_type": "Per", "Text": "giant", "Start": "733", "End": "734"}, {"Entity_type": "Fac", "Text": "church", "Start": "759", "End": "760"}, {"Entity_type": "Fac", "Text": "church", "Start": "857", "End": "858"}, {"Entity_type": "Fac", "Text": "church", "Start": "234", "End": "235"}, {"Entity_type": "Fac", "Text": "church", "Start": "338", "End": "339"}, {"Entity_type": "Fac", "Text": "church", "Start": "647", "End": "648"}, {"Entity_type": "Per", "Text": "giant", "Start": "810", "End": "811"}, {"Entity_type": "Per", "Text": " wife", "Start": "815", "End": "817"}, {"Entity_type": "Per", "Text": "minster", "Start": "51", "End": "52"}, {"Entity_type": "Per", "Text": "minster", "Start": "84", "End": "85"}, {"Entity_type": "Loc", "Text": "town", "Start": "439", "End": "440"}]