[{"Relation_type": "GEN-AFF (Gen-affiliation)", "Relation_subtype": "Citizen-Resident-Religion-Ethnicity", "Arguments": [{"Arg_type": "Arg1", "Text": "\u9f4a\u570b\u76f8\u570b", "Start": "7", "End": "11"}, {"Arg_type": "Arg2", "Text": "\u9f4a\u570b", "Start": "7", "End": "9"}]}, {"Relation_type": "GEN-AFF (Gen-affiliation)", "Relation_subtype": "Citizen-Resident-Religion-Ethnicity", "Arguments": [{"Arg_type": "Arg1", "Text": "\u5b64\u7af9\u570b\u738b", "Start": "99", "End": "103"}, {"Arg_type": "Arg2", "Text": "\u5b64\u7af9", "Start": "99", "End": "101"}]}, {"Relation_type": "PHYS (physical)", "Relation_subtype": "Located", "Arguments": [{"Arg_type": "Arg1", "Text": "\u9077\u5b89\u5e02\u5357\u90e8", "Start": "195", "End": "200"}, {"Arg_type": "Arg2", "Text": "\u9077\u5b89\u5e02", "Start": "195", "End": "198"}]}, {"Relation_type": "Coreference", "Relation_subtype": "Coref", "Arguments": [{"Arg_type": "Arg1", "Text": "\u8001\u99ac", "Start": "354", "End": "356"}, {"Arg_type": "Arg2", "Text": "\u5b83\u5011", "Start": "363", "End": "365"}]}]