[{"Event_type": "Movement", "Event_subtype": "Transport", "Arguments": [{"Arg_type": "Trigger_Word", "Text": "came", "Start": "141", "End": "142"}, {"Arg_type": "Agent", "Text": "St. Lawrence", "Start": "136", "End": "140"}, {"Arg_type": "Destination", "Text": "Lund", "Start": "145", "End": "146"}]}, {"Event_type": "Process", "Event_subtype": "Process", "Arguments": [{"Arg_type": "Trigger_word", "Text": "build", "Start": "162", "End": "163"}, {"Arg_type": "Entity", "Text": "he", "Start": "156", "End": "157"}, {"Arg_type": "Trigger_word", "Text": "church", "Start": "166", "End": "167"}]}, {"Event_type": "State", "Event_subtype": "Thought", "Arguments": [{"Arg_type": "Trigger_word", "Text": "cudgelling", "Start": "203", "End": "204"}, {"Arg_type": "Entity", "Text": "he", "Start": "199", "End": "200"}]}, {"Event_type": "Contact", "Event_subtype": "Meet", "Arguments": [{"Arg_type": "Trigger_Word", "Text": "came", "Start": "218", "End": "219"}, {"Arg_type": "Entity", "Text": "giant", "Start": "216", "End": "217"}, {"Arg_type": "Entity", "Text": "him", "Start": "222", "End": "223"}]}, {"Event_type": "Process", "Event_subtype": "Process", "Arguments": [{"Arg_type": "Trigger_word", "Text": "building", "Start": "332", "End": "333"}, {"Arg_type": "Entity", "Text": "church", "Start": "338", "End": "339"}]}, {"Event_type": "State", "Event_subtype": "Thought", "Arguments": [{"Arg_type": "Trigger_word", "Text": "thought", "Start": "367", "End": "368"}, {"Arg_type": "Entity", "Text": "St. Lawrence ", "Start": "362", "End": "367"}]}, {"Event_type": "Movement", "Event_subtype": "Transport", "Arguments": [{"Arg_type": "Trigger_Word", "Text": "walking", "Start": "433", "End": "434"}, {"Arg_type": "Agent", "Text": "he", "Start": "429", "End": "430"}]}, {"Event_type": "Movement", "Event_subtype": "Transport", "Arguments": [{"Arg_type": "Trigger_Word", "Text": "ran", "Start": "628", "End": "629"}, {"Arg_type": "Destination", "Text": "town", "Start": "636", "End": "637"}, {"Arg_type": "Agent", "Text": "He", "Start": "626", "End": "627"}]}, {"Event_type": "State", "Event_subtype": "Emotion", "Arguments": [{"Arg_type": "Trigger_word", "Text": "rage", "Start": "750", "End": "751"}, {"Arg_type": "Entity", "Text": "giant", "Start": "733", "End": "734"}]}]