[{"Event_type": "State", "Event_subtype": "Emotion", "Arguments": [{"Arg_type": "Trigger_word", "Text": "smiled", "Start": "654", "End": "655"}, {"Arg_type": "Entity", "Text": "Old Adam", "Start": "650", "End": "653"}]}, {"Event_type": "State", "Event_subtype": "Emotion", "Arguments": [{"Arg_type": "Entity", "Text": "Maria", "Start": "693", "End": "694"}, {"Arg_type": "Trigger_word", "Text": "surprisingly", "Start": "697", "End": "698"}]}, {"Event_type": "State", "Event_subtype": "Emotion", "Arguments": [{"Arg_type": "Trigger_word", "Text": "confused", "Start": "710", "End": "711"}, {"Arg_type": "Entity", "Text": "Old Adam", "Start": "700", "End": "703"}]}, {"Event_type": "Conflict", "Event_subtype": "Attack", "Arguments": [{"Arg_type": "Target", "Text": "Sugar", "Start": "971", "End": "972"}, {"Arg_type": "Attacker", "Text": "Salt", "Start": "967", "End": "968"}, {"Arg_type": "Trigger_Word", "Text": "fight", "Start": "983", "End": "984"}]}]